[
    {
        "sha": "dcbfcc6ec9336c2219dbff008a560b991af97491",
        "node_id": "MDY6Q29tbWl0Njk2MzMyODk6ZGNiZmNjNmVjOTMzNmMyMjE5ZGJmZjAwOGE1NjBiOTkxYWY5NzQ5MQ==",
        "commit": {
            "author": {
                "name": "youhusky",
                "email": "bozhaoli.usc@gmail.com",
                "date": "2018-04-14T01:56:32Z"
            },
            "committer": {
                "name": "youhusky",
                "email": "bozhaoli.usc@gmail.com",
                "date": "2018-04-14T01:56:32Z"
            },
            "message": "blog",
            "tree": {
                "sha": "f8446ef51fe9f4e1908426bbc090f29eea4be653",
                "url": "https://api.github.com/repos/youhusky/youhusky.github.io/git/trees/f8446ef51fe9f4e1908426bbc090f29eea4be653"
            },
            "url": "https://api.github.com/repos/youhusky/youhusky.github.io/git/commits/dcbfcc6ec9336c2219dbff008a560b991af97491",
            "comment_count": 0,
            "verification": {
                "verified": false,
                "reason": "unsigned",
                "signature": null,
                "payload": null
            }
        },
        "url": "https://api.github.com/repos/youhusky/youhusky.github.io/commits/dcbfcc6ec9336c2219dbff008a560b991af97491",
        "html_url": "https://github.com/youhusky/youhusky.github.io/commit/dcbfcc6ec9336c2219dbff008a560b991af97491",
        "comments_url": "https://api.github.com/repos/youhusky/youhusky.github.io/commits/dcbfcc6ec9336c2219dbff008a560b991af97491/comments",
        "author": {
            "login": "youhusky",
            "id": 10191895,
            "node_id": "MDQ6VXNlcjEwMTkxODk1",
            "avatar_url": "https://avatars3.githubusercontent.com/u/10191895?v=4",
            "gravatar_id": "",
            "url": "https://api.github.com/users/youhusky",
            "html_url": "https://github.com/youhusky",
            "followers_url": "https://api.github.com/users/youhusky/followers",
            "following_url": "https://api.github.com/users/youhusky/following{/other_user}",
            "gists_url": "https://api.github.com/users/youhusky/gists{/gist_id}",
            "starred_url": "https://api.github.com/users/youhusky/starred{/owner}{/repo}",
            "subscriptions_url": "https://api.github.com/users/youhusky/subscriptions",
            "organizations_url": "https://api.github.com/users/youhusky/orgs",
            "repos_url": "https://api.github.com/users/youhusky/repos",
            "events_url": "https://api.github.com/users/youhusky/events{/privacy}",
            "received_events_url": "https://api.github.com/users/youhusky/received_events",
            "type": "User",
            "site_admin": false
        },
        "committer": {
            "login": "youhusky",
            "id": 10191895,
            "node_id": "MDQ6VXNlcjEwMTkxODk1",
            "avatar_url": "https://avatars3.githubusercontent.com/u/10191895?v=4",
            "gravatar_id": "",
            "url": "https://api.github.com/users/youhusky",
            "html_url": "https://github.com/youhusky",
            "followers_url": "https://api.github.com/users/youhusky/followers",
            "following_url": "https://api.github.com/users/youhusky/following{/other_user}",
            "gists_url": "https://api.github.com/users/youhusky/gists{/gist_id}",
            "starred_url": "https://api.github.com/users/youhusky/starred{/owner}{/repo}",
            "subscriptions_url": "https://api.github.com/users/youhusky/subscriptions",
            "organizations_url": "https://api.github.com/users/youhusky/orgs",
            "repos_url": "https://api.github.com/users/youhusky/repos",
            "events_url": "https://api.github.com/users/youhusky/events{/privacy}",
            "received_events_url": "https://api.github.com/users/youhusky/received_events",
            "type": "User",
            "site_admin": false
        },
        "parents": [
            {
                "sha": "44f12ae0ad15a713222a04ed0e6a0dd6d17e5ef9",
                "url": "https://api.github.com/repos/youhusky/youhusky.github.io/commits/44f12ae0ad15a713222a04ed0e6a0dd6d17e5ef9",
                "html_url": "https://github.com/youhusky/youhusky.github.io/commit/44f12ae0ad15a713222a04ed0e6a0dd6d17e5ef9"
            }
        ]
    },
    {
        "sha": "44f12ae0ad15a713222a04ed0e6a0dd6d17e5ef9",
        "node_id": "MDY6Q29tbWl0Njk2MzMyODk6NDRmMTJhZTBhZDE1YTcxMzIyMmEwNGVkMGU2YTBkZDZkMTdlNWVmOQ==",
        "commit": {
            "author": {
                "name": "Bozhao Li",
                "email": "youhusky@126.com",
                "date": "2017-04-20T05:03:33Z"
            },
            "committer": {
                "name": "Bozhao Li",
                "email": "youhusky@126.com",
                "date": "2017-04-20T05:03:33Z"
            },
            "message": "blog",
            "tree": {
                "sha": "e598d12d3186486884f60db06eb2b8098bc7b554",
                "url": "https://api.github.com/repos/youhusky/youhusky.github.io/git/trees/e598d12d3186486884f60db06eb2b8098bc7b554"
            },
            "url": "https://api.github.com/repos/youhusky/youhusky.github.io/git/commits/44f12ae0ad15a713222a04ed0e6a0dd6d17e5ef9",
            "comment_count": 0,
            "verification": {
                "verified": false,
                "reason": "unsigned",
                "signature": null,
                "payload": null
            }
        },
        "url": "https://api.github.com/repos/youhusky/youhusky.github.io/commits/44f12ae0ad15a713222a04ed0e6a0dd6d17e5ef9",
        "html_url": "https://github.com/youhusky/youhusky.github.io/commit/44f12ae0ad15a713222a04ed0e6a0dd6d17e5ef9",
        "comments_url": "https://api.github.com/repos/youhusky/youhusky.github.io/commits/44f12ae0ad15a713222a04ed0e6a0dd6d17e5ef9/comments",
        "author": null,
        "committer": null,
        "parents": [
            {
                "sha": "f059e5bb9a9f3db4c89e62484891c55cb54fad0b",
                "url": "https://api.github.com/repos/youhusky/youhusky.github.io/commits/f059e5bb9a9f3db4c89e62484891c55cb54fad0b",
                "html_url": "https://github.com/youhusky/youhusky.github.io/commit/f059e5bb9a9f3db4c89e62484891c55cb54fad0b"
            }
        ]
    },
    {
        "sha": "f059e5bb9a9f3db4c89e62484891c55cb54fad0b",
        "node_id": "MDY6Q29tbWl0Njk2MzMyODk6ZjA1OWU1YmI5YTlmM2RiNGM4OWU2MjQ4NDg5MWM1NWNiNTRmYWQwYg==",
        "commit": {
            "author": {
                "name": "Bozhao Li",
                "email": "youhusky@126.com",
                "date": "2017-04-20T05:02:39Z"
            },
            "committer": {
                "name": "Bozhao Li",
                "email": "youhusky@126.com",
                "date": "2017-04-20T05:02:39Z"
            },
            "message": "blog",
            "tree": {
                "sha": "4c587bc90824bc47637e45cb5a5cad86b3b1dafd",
                "url": "https://api.github.com/repos/youhusky/youhusky.github.io/git/trees/4c587bc90824bc47637e45cb5a5cad86b3b1dafd"
            },
            "url": "https://api.github.com/repos/youhusky/youhusky.github.io/git/commits/f059e5bb9a9f3db4c89e62484891c55cb54fad0b",
            "comment_count": 0,
            "verification": {
                "verified": false,
                "reason": "unsigned",
                "signature": null,
                "payload": null
            }
        },
        "url": "https://api.github.com/repos/youhusky/youhusky.github.io/commits/f059e5bb9a9f3db4c89e62484891c55cb54fad0b",
        "html_url": "https://github.com/youhusky/youhusky.github.io/commit/f059e5bb9a9f3db4c89e62484891c55cb54fad0b",
        "comments_url": "https://api.github.com/repos/youhusky/youhusky.github.io/commits/f059e5bb9a9f3db4c89e62484891c55cb54fad0b/comments",
        "author": null,
        "committer": null,
        "parents": [
            {
                "sha": "d0293dd93bcf7b7854a2a7c4cb4559cdf008da6c",
                "url": "https://api.github.com/repos/youhusky/youhusky.github.io/commits/d0293dd93bcf7b7854a2a7c4cb4559cdf008da6c",
                "html_url": "https://github.com/youhusky/youhusky.github.io/commit/d0293dd93bcf7b7854a2a7c4cb4559cdf008da6c"
            }
        ]
    },
    {
        "sha": "d0293dd93bcf7b7854a2a7c4cb4559cdf008da6c",
        "node_id": "MDY6Q29tbWl0Njk2MzMyODk6ZDAyOTNkZDkzYmNmN2I3ODU0YTJhN2M0Y2I0NTU5Y2RmMDA4ZGE2Yw==",
        "commit": {
            "author": {
                "name": "Bozhao Li",
                "email": "youhusky@126.com",
                "date": "2016-12-03T05:50:06Z"
            },
            "committer": {
                "name": "Bozhao Li",
                "email": "youhusky@126.com",
                "date": "2016-12-03T05:50:06Z"
            },
            "message": "readme.me",
            "tree": {
                "sha": "b9a8bd971abb6fda027916244eb9c75e8fed388f",
                "url": "https://api.github.com/repos/youhusky/youhusky.github.io/git/trees/b9a8bd971abb6fda027916244eb9c75e8fed388f"
            },
            "url": "https://api.github.com/repos/youhusky/youhusky.github.io/git/commits/d0293dd93bcf7b7854a2a7c4cb4559cdf008da6c",
            "comment_count": 0,
            "verification": {
                "verified": false,
                "reason": "unsigned",
                "signature": null,
                "payload": null
            }
        },
        "url": "https://api.github.com/repos/youhusky/youhusky.github.io/commits/d0293dd93bcf7b7854a2a7c4cb4559cdf008da6c",
        "html_url": "https://github.com/youhusky/youhusky.github.io/commit/d0293dd93bcf7b7854a2a7c4cb4559cdf008da6c",
        "comments_url": "https://api.github.com/repos/youhusky/youhusky.github.io/commits/d0293dd93bcf7b7854a2a7c4cb4559cdf008da6c/comments",
        "author": null,
        "committer": null,
        "parents": [
            {
                "sha": "549bb53249b63b3d12df9d6d21ebd89c41a3be15",
                "url": "https://api.github.com/repos/youhusky/youhusky.github.io/commits/549bb53249b63b3d12df9d6d21ebd89c41a3be15",
                "html_url": "https://github.com/youhusky/youhusky.github.io/commit/549bb53249b63b3d12df9d6d21ebd89c41a3be15"
            }
        ]
    },
    {
        "sha": "549bb53249b63b3d12df9d6d21ebd89c41a3be15",
        "node_id": "MDY6Q29tbWl0Njk2MzMyODk6NTQ5YmI1MzI0OWI2M2IzZDEyZGY5ZDZkMjFlYmQ4OWM0MWEzYmUxNQ==",
        "commit": {
            "author": {
                "name": "Bozhao Li",
                "email": "youhusky@126.com",
                "date": "2016-12-03T05:19:18Z"
            },
            "committer": {
                "name": "Bozhao Li",
                "email": "youhusky@126.com",
                "date": "2016-12-03T05:19:18Z"
            },
            "message": "paper",
            "tree": {
                "sha": "5873a81853a87d472d0f29e71896d58bf980f517",
                "url": "https://api.github.com/repos/youhusky/youhusky.github.io/git/trees/5873a81853a87d472d0f29e71896d58bf980f517"
            },
            "url": "https://api.github.com/repos/youhusky/youhusky.github.io/git/commits/549bb53249b63b3d12df9d6d21ebd89c41a3be15",
            "comment_count": 0,
            "verification": {
                "verified": false,
                "reason": "unsigned",
                "signature": null,
                "payload": null
            }
        },
        "url": "https://api.github.com/repos/youhusky/youhusky.github.io/commits/549bb53249b63b3d12df9d6d21ebd89c41a3be15",
        "html_url": "https://github.com/youhusky/youhusky.github.io/commit/549bb53249b63b3d12df9d6d21ebd89c41a3be15",
        "comments_url": "https://api.github.com/repos/youhusky/youhusky.github.io/commits/549bb53249b63b3d12df9d6d21ebd89c41a3be15/comments",
        "author": null,
        "committer": null,
        "parents": [
            {
                "sha": "b2905add48fd982d2f0faefb001a26e2e1dace20",
                "url": "https://api.github.com/repos/youhusky/youhusky.github.io/commits/b2905add48fd982d2f0faefb001a26e2e1dace20",
                "html_url": "https://github.com/youhusky/youhusky.github.io/commit/b2905add48fd982d2f0faefb001a26e2e1dace20"
            }
        ]
    },
    {
        "sha": "b2905add48fd982d2f0faefb001a26e2e1dace20",
        "node_id": "MDY6Q29tbWl0Njk2MzMyODk6YjI5MDVhZGQ0OGZkOTgyZDJmMGZhZWZiMDAxYTI2ZTJlMWRhY2UyMA==",
        "commit": {
            "author": {
                "name": "Bozhao Li",
                "email": "youhusky@126.com",
                "date": "2016-12-02T23:40:07Z"
            },
            "committer": {
                "name": "Bozhao Li",
                "email": "youhusky@126.com",
                "date": "2016-12-02T23:40:07Z"
            },
            "message": "1202-joshua",
            "tree": {
                "sha": "351d856eb950d46140f2212dc62ee9c171ee09f1",
                "url": "https://api.github.com/repos/youhusky/youhusky.github.io/git/trees/351d856eb950d46140f2212dc62ee9c171ee09f1"
            },
            "url": "https://api.github.com/repos/youhusky/youhusky.github.io/git/commits/b2905add48fd982d2f0faefb001a26e2e1dace20",
            "comment_count": 0,
            "verification": {
                "verified": false,
                "reason": "unsigned",
                "signature": null,
                "payload": null
            }
        },
        "url": "https://api.github.com/repos/youhusky/youhusky.github.io/commits/b2905add48fd982d2f0faefb001a26e2e1dace20",
        "html_url": "https://github.com/youhusky/youhusky.github.io/commit/b2905add48fd982d2f0faefb001a26e2e1dace20",
        "comments_url": "https://api.github.com/repos/youhusky/youhusky.github.io/commits/b2905add48fd982d2f0faefb001a26e2e1dace20/comments",
        "author": null,
        "committer": null,
        "parents": [
            {
                "sha": "6d949e496e96f53b37b50af490538b8cabee9cbc",
                "url": "https://api.github.com/repos/youhusky/youhusky.github.io/commits/6d949e496e96f53b37b50af490538b8cabee9cbc",
                "html_url": "https://github.com/youhusky/youhusky.github.io/commit/6d949e496e96f53b37b50af490538b8cabee9cbc"
            }
        ]
    },
    {
        "sha": "6d949e496e96f53b37b50af490538b8cabee9cbc",
        "node_id": "MDY6Q29tbWl0Njk2MzMyODk6NmQ5NDllNDk2ZTk2ZjUzYjM3YjUwYWY0OTA1MzhiOGNhYmVlOWNiYw==",
        "commit": {
            "author": {
                "name": "Bozhao Li",
                "email": "youhusky@126.com",
                "date": "2016-12-02T09:55:16Z"
            },
            "committer": {
                "name": "Bozhao Li",
                "email": "youhusky@126.com",
                "date": "2016-12-02T09:55:16Z"
            },
            "message": "modify index",
            "tree": {
                "sha": "822d223cbd1348950d27386d6cd2086ad31de5b0",
                "url": "https://api.github.com/repos/youhusky/youhusky.github.io/git/trees/822d223cbd1348950d27386d6cd2086ad31de5b0"
            },
            "url": "https://api.github.com/repos/youhusky/youhusky.github.io/git/commits/6d949e496e96f53b37b50af490538b8cabee9cbc",
            "comment_count": 0,
            "verification": {
                "verified": false,
                "reason": "unsigned",
                "signature": null,
                "payload": null
            }
        },
        "url": "https://api.github.com/repos/youhusky/youhusky.github.io/commits/6d949e496e96f53b37b50af490538b8cabee9cbc",
        "html_url": "https://github.com/youhusky/youhusky.github.io/commit/6d949e496e96f53b37b50af490538b8cabee9cbc",
        "comments_url": "https://api.github.com/repos/youhusky/youhusky.github.io/commits/6d949e496e96f53b37b50af490538b8cabee9cbc/comments",
        "author": null,
        "committer": null,
        "parents": [
            {
                "sha": "f61f54281a441b2b79d8af3244fc56b0018f4e2c",
                "url": "https://api.github.com/repos/youhusky/youhusky.github.io/commits/f61f54281a441b2b79d8af3244fc56b0018f4e2c",
                "html_url": "https://github.com/youhusky/youhusky.github.io/commit/f61f54281a441b2b79d8af3244fc56b0018f4e2c"
            }
        ]
    },
    {
        "sha": "f61f54281a441b2b79d8af3244fc56b0018f4e2c",
        "node_id": "MDY6Q29tbWl0Njk2MzMyODk6ZjYxZjU0MjgxYTQ0MWIyYjc5ZDhhZjMyNDRmYzU2YjAwMThmNGUyYw==",
        "commit": {
            "author": {
                "name": "Bozhao Li",
                "email": "youhusky@126.com",
                "date": "2016-12-02T09:32:23Z"
            },
            "committer": {
                "name": "Bozhao Li",
                "email": "youhusky@126.com",
                "date": "2016-12-02T09:32:23Z"
            },
            "message": "1202",
            "tree": {
                "sha": "c105a9830407cc39cb30e1bd10c4a61ea833568d",
                "url": "https://api.github.com/repos/youhusky/youhusky.github.io/git/trees/c105a9830407cc39cb30e1bd10c4a61ea833568d"
            },
            "url": "https://api.github.com/repos/youhusky/youhusky.github.io/git/commits/f61f54281a441b2b79d8af3244fc56b0018f4e2c",
            "comment_count": 0,
            "verification": {
                "verified": false,
                "reason": "unsigned",
                "signature": null,
                "payload": null
            }
        },
        "url": "https://api.github.com/repos/youhusky/youhusky.github.io/commits/f61f54281a441b2b79d8af3244fc56b0018f4e2c",
        "html_url": "https://github.com/youhusky/youhusky.github.io/commit/f61f54281a441b2b79d8af3244fc56b0018f4e2c",
        "comments_url": "https://api.github.com/repos/youhusky/youhusky.github.io/commits/f61f54281a441b2b79d8af3244fc56b0018f4e2c/comments",
        "author": null,
        "committer": null,
        "parents": [
            {
                "sha": "93c7aa11e1b684c1e4dc5b2a52f6b94ab43ad649",
                "url": "https://api.github.com/repos/youhusky/youhusky.github.io/commits/93c7aa11e1b684c1e4dc5b2a52f6b94ab43ad649",
                "html_url": "https://github.com/youhusky/youhusky.github.io/commit/93c7aa11e1b684c1e4dc5b2a52f6b94ab43ad649"
            }
        ]
    },
    {
        "sha": "93c7aa11e1b684c1e4dc5b2a52f6b94ab43ad649",
        "node_id": "MDY6Q29tbWl0Njk2MzMyODk6OTNjN2FhMTFlMWI2ODRjMWU0ZGM1YjJhNTJmNmI5NGFiNDNhZDY0OQ==",
        "commit": {
            "author": {
                "name": "Bozhao Li",
                "email": "youhusky@126.com",
                "date": "2016-12-02T02:54:55Z"
            },
            "committer": {
                "name": "Bozhao Li",
                "email": "youhusky@126.com",
                "date": "2016-12-02T02:54:55Z"
            },
            "message": "1201",
            "tree": {
                "sha": "56d15697b87a148a4e613cf8b4fceec422cebc40",
                "url": "https://api.github.com/repos/youhusky/youhusky.github.io/git/trees/56d15697b87a148a4e613cf8b4fceec422cebc40"
            },
            "url": "https://api.github.com/repos/youhusky/youhusky.github.io/git/commits/93c7aa11e1b684c1e4dc5b2a52f6b94ab43ad649",
            "comment_count": 0,
            "verification": {
                "verified": false,
                "reason": "unsigned",
                "signature": null,
                "payload": null
            }
        },
        "url": "https://api.github.com/repos/youhusky/youhusky.github.io/commits/93c7aa11e1b684c1e4dc5b2a52f6b94ab43ad649",
        "html_url": "https://github.com/youhusky/youhusky.github.io/commit/93c7aa11e1b684c1e4dc5b2a52f6b94ab43ad649",
        "comments_url": "https://api.github.com/repos/youhusky/youhusky.github.io/commits/93c7aa11e1b684c1e4dc5b2a52f6b94ab43ad649/comments",
        "author": null,
        "committer": null,
        "parents": [
            {
                "sha": "c51264af7f8e3bd9102477ce2fa1bf267a5e0e72",
                "url": "https://api.github.com/repos/youhusky/youhusky.github.io/commits/c51264af7f8e3bd9102477ce2fa1bf267a5e0e72",
                "html_url": "https://github.com/youhusky/youhusky.github.io/commit/c51264af7f8e3bd9102477ce2fa1bf267a5e0e72"
            }
        ]
    },
    {
        "sha": "c51264af7f8e3bd9102477ce2fa1bf267a5e0e72",
        "node_id": "MDY6Q29tbWl0Njk2MzMyODk6YzUxMjY0YWY3ZjhlM2JkOTEwMjQ3N2NlMmZhMWJmMjY3YTVlMGU3Mg==",
        "commit": {
            "author": {
                "name": "Bozhao Li",
                "email": "youhusky@126.com",
                "date": "2016-12-01T04:56:19Z"
            },
            "committer": {
                "name": "Bozhao Li",
                "email": "youhusky@126.com",
                "date": "2016-12-01T04:56:19Z"
            },
            "message": "1130-2055",
            "tree": {
                "sha": "884b64fc537b01dd8ef9ed1e5fd43694d36cd625",
                "url": "https://api.github.com/repos/youhusky/youhusky.github.io/git/trees/884b64fc537b01dd8ef9ed1e5fd43694d36cd625"
            },
            "url": "https://api.github.com/repos/youhusky/youhusky.github.io/git/commits/c51264af7f8e3bd9102477ce2fa1bf267a5e0e72",
            "comment_count": 0,
            "verification": {
                "verified": false,
                "reason": "unsigned",
                "signature": null,
                "payload": null
            }
        },
        "url": "https://api.github.com/repos/youhusky/youhusky.github.io/commits/c51264af7f8e3bd9102477ce2fa1bf267a5e0e72",
        "html_url": "https://github.com/youhusky/youhusky.github.io/commit/c51264af7f8e3bd9102477ce2fa1bf267a5e0e72",
        "comments_url": "https://api.github.com/repos/youhusky/youhusky.github.io/commits/c51264af7f8e3bd9102477ce2fa1bf267a5e0e72/comments",
        "author": null,
        "committer": null,
        "parents": [
            {
                "sha": "30cf82ff77f491b559d4f08f9784a6860cfb60db",
                "url": "https://api.github.com/repos/youhusky/youhusky.github.io/commits/30cf82ff77f491b559d4f08f9784a6860cfb60db",
                "html_url": "https://github.com/youhusky/youhusky.github.io/commit/30cf82ff77f491b559d4f08f9784a6860cfb60db"
            }
        ]
    },
    {
        "sha": "30cf82ff77f491b559d4f08f9784a6860cfb60db",
        "node_id": "MDY6Q29tbWl0Njk2MzMyODk6MzBjZjgyZmY3N2Y0OTFiNTU5ZDRmMDhmOTc4NGE2ODYwY2ZiNjBkYg==",
        "commit": {
            "author": {
                "name": "Bozhao Li",
                "email": "youhusky@126.com",
                "date": "2016-12-01T04:08:21Z"
            },
            "committer": {
                "name": "Bozhao Li",
                "email": "youhusky@126.com",
                "date": "2016-12-01T04:08:21Z"
            },
            "message": "1130-modify",
            "tree": {
                "sha": "df5bb83b6bb02d04a33d84a1e6483bd85c43abde",
                "url": "https://api.github.com/repos/youhusky/youhusky.github.io/git/trees/df5bb83b6bb02d04a33d84a1e6483bd85c43abde"
            },
            "url": "https://api.github.com/repos/youhusky/youhusky.github.io/git/commits/30cf82ff77f491b559d4f08f9784a6860cfb60db",
            "comment_count": 0,
            "verification": {
                "verified": false,
                "reason": "unsigned",
                "signature": null,
                "payload": null
            }
        },
        "url": "https://api.github.com/repos/youhusky/youhusky.github.io/commits/30cf82ff77f491b559d4f08f9784a6860cfb60db",
        "html_url": "https://github.com/youhusky/youhusky.github.io/commit/30cf82ff77f491b559d4f08f9784a6860cfb60db",
        "comments_url": "https://api.github.com/repos/youhusky/youhusky.github.io/commits/30cf82ff77f491b559d4f08f9784a6860cfb60db/comments",
        "author": null,
        "committer": null,
        "parents": [
            {
                "sha": "be8b2b4033802a51163d046ea23c5617eb9b122b",
                "url": "https://api.github.com/repos/youhusky/youhusky.github.io/commits/be8b2b4033802a51163d046ea23c5617eb9b122b",
                "html_url": "https://github.com/youhusky/youhusky.github.io/commit/be8b2b4033802a51163d046ea23c5617eb9b122b"
            }
        ]
    },
    {
        "sha": "be8b2b4033802a51163d046ea23c5617eb9b122b",
        "node_id": "MDY6Q29tbWl0Njk2MzMyODk6YmU4YjJiNDAzMzgwMmE1MTE2M2QwNDZlYTIzYzU2MTdlYjliMTIyYg==",
        "commit": {
            "author": {
                "name": "Bozhao Li",
                "email": "youhusky@126.com",
                "date": "2016-11-30T10:38:58Z"
            },
            "committer": {
                "name": "Bozhao Li",
                "email": "youhusky@126.com",
                "date": "2016-11-30T10:38:58Z"
            },
            "message": "1130",
            "tree": {
                "sha": "df18f3b4844b276abf0614fea769aa90045b434c",
                "url": "https://api.github.com/repos/youhusky/youhusky.github.io/git/trees/df18f3b4844b276abf0614fea769aa90045b434c"
            },
            "url": "https://api.github.com/repos/youhusky/youhusky.github.io/git/commits/be8b2b4033802a51163d046ea23c5617eb9b122b",
            "comment_count": 0,
            "verification": {
                "verified": false,
                "reason": "unsigned",
                "signature": null,
                "payload": null
            }
        },
        "url": "https://api.github.com/repos/youhusky/youhusky.github.io/commits/be8b2b4033802a51163d046ea23c5617eb9b122b",
        "html_url": "https://github.com/youhusky/youhusky.github.io/commit/be8b2b4033802a51163d046ea23c5617eb9b122b",
        "comments_url": "https://api.github.com/repos/youhusky/youhusky.github.io/commits/be8b2b4033802a51163d046ea23c5617eb9b122b/comments",
        "author": null,
        "committer": null,
        "parents": [
            {
                "sha": "4f7e7cb6a41d06fddf74c25b16829825d97600ce",
                "url": "https://api.github.com/repos/youhusky/youhusky.github.io/commits/4f7e7cb6a41d06fddf74c25b16829825d97600ce",
                "html_url": "https://github.com/youhusky/youhusky.github.io/commit/4f7e7cb6a41d06fddf74c25b16829825d97600ce"
            }
        ]
    },
    {
        "sha": "4f7e7cb6a41d06fddf74c25b16829825d97600ce",
        "node_id": "MDY6Q29tbWl0Njk2MzMyODk6NGY3ZTdjYjZhNDFkMDZmZGRmNzRjMjViMTY4Mjk4MjVkOTc2MDBjZQ==",
        "commit": {
            "author": {
                "name": "Bozhao Li",
                "email": "youhusky@126.com",
                "date": "2016-11-30T09:15:04Z"
            },
            "committer": {
                "name": "Bozhao Li",
                "email": "youhusky@126.com",
                "date": "2016-11-30T09:15:04Z"
            },
            "message": "1130",
            "tree": {
                "sha": "4ae275e3287289c7b50c019a549814f66e3e3b84",
                "url": "https://api.github.com/repos/youhusky/youhusky.github.io/git/trees/4ae275e3287289c7b50c019a549814f66e3e3b84"
            },
            "url": "https://api.github.com/repos/youhusky/youhusky.github.io/git/commits/4f7e7cb6a41d06fddf74c25b16829825d97600ce",
            "comment_count": 0,
            "verification": {
                "verified": false,
                "reason": "unsigned",
                "signature": null,
                "payload": null
            }
        },
        "url": "https://api.github.com/repos/youhusky/youhusky.github.io/commits/4f7e7cb6a41d06fddf74c25b16829825d97600ce",
        "html_url": "https://github.com/youhusky/youhusky.github.io/commit/4f7e7cb6a41d06fddf74c25b16829825d97600ce",
        "comments_url": "https://api.github.com/repos/youhusky/youhusky.github.io/commits/4f7e7cb6a41d06fddf74c25b16829825d97600ce/comments",
        "author": null,
        "committer": null,
        "parents": [
            {
                "sha": "f08a21561da8887b5c5fd4d85bce74bc2364979b",
                "url": "https://api.github.com/repos/youhusky/youhusky.github.io/commits/f08a21561da8887b5c5fd4d85bce74bc2364979b",
                "html_url": "https://github.com/youhusky/youhusky.github.io/commit/f08a21561da8887b5c5fd4d85bce74bc2364979b"
            }
        ]
    },
    {
        "sha": "f08a21561da8887b5c5fd4d85bce74bc2364979b",
        "node_id": "MDY6Q29tbWl0Njk2MzMyODk6ZjA4YTIxNTYxZGE4ODg3YjVjNWZkNGQ4NWJjZTc0YmMyMzY0OTc5Yg==",
        "commit": {
            "author": {
                "name": "Bozhao Li",
                "email": "youhusky@126.com",
                "date": "2016-11-30T08:48:14Z"
            },
            "committer": {
                "name": "Bozhao Li",
                "email": "youhusky@126.com",
                "date": "2016-11-30T08:48:14Z"
            },
            "message": "1130",
            "tree": {
                "sha": "5567d17a9112859c3a466e23ce7ace79b806b073",
                "url": "https://api.github.com/repos/youhusky/youhusky.github.io/git/trees/5567d17a9112859c3a466e23ce7ace79b806b073"
            },
            "url": "https://api.github.com/repos/youhusky/youhusky.github.io/git/commits/f08a21561da8887b5c5fd4d85bce74bc2364979b",
            "comment_count": 0,
            "verification": {
                "verified": false,
                "reason": "unsigned",
                "signature": null,
                "payload": null
            }
        },
        "url": "https://api.github.com/repos/youhusky/youhusky.github.io/commits/f08a21561da8887b5c5fd4d85bce74bc2364979b",
        "html_url": "https://github.com/youhusky/youhusky.github.io/commit/f08a21561da8887b5c5fd4d85bce74bc2364979b",
        "comments_url": "https://api.github.com/repos/youhusky/youhusky.github.io/commits/f08a21561da8887b5c5fd4d85bce74bc2364979b/comments",
        "author": null,
        "committer": null,
        "parents": [
            {
                "sha": "30ccca9b2fc8c88b1d37c4bb595a8ec60414a4c8",
                "url": "https://api.github.com/repos/youhusky/youhusky.github.io/commits/30ccca9b2fc8c88b1d37c4bb595a8ec60414a4c8",
                "html_url": "https://github.com/youhusky/youhusky.github.io/commit/30ccca9b2fc8c88b1d37c4bb595a8ec60414a4c8"
            }
        ]
    },
    {
        "sha": "30ccca9b2fc8c88b1d37c4bb595a8ec60414a4c8",
        "node_id": "MDY6Q29tbWl0Njk2MzMyODk6MzBjY2NhOWIyZmM4Yzg4YjFkMzdjNGJiNTk1YThlYzYwNDE0YTRjOA==",
        "commit": {
            "author": {
                "name": "Bozhao Li",
                "email": "youhusky@126.com",
                "date": "2016-11-30T05:39:21Z"
            },
            "committer": {
                "name": "Bozhao Li",
                "email": "youhusky@126.com",
                "date": "2016-11-30T05:39:21Z"
            },
            "message": "1129-nav",
            "tree": {
                "sha": "d39689c4eb4505da974701a0fdacb3cb2bd32860",
                "url": "https://api.github.com/repos/youhusky/youhusky.github.io/git/trees/d39689c4eb4505da974701a0fdacb3cb2bd32860"
            },
            "url": "https://api.github.com/repos/youhusky/youhusky.github.io/git/commits/30ccca9b2fc8c88b1d37c4bb595a8ec60414a4c8",
            "comment_count": 0,
            "verification": {
                "verified": false,
                "reason": "unsigned",
                "signature": null,
                "payload": null
            }
        },
        "url": "https://api.github.com/repos/youhusky/youhusky.github.io/commits/30ccca9b2fc8c88b1d37c4bb595a8ec60414a4c8",
        "html_url": "https://github.com/youhusky/youhusky.github.io/commit/30ccca9b2fc8c88b1d37c4bb595a8ec60414a4c8",
        "comments_url": "https://api.github.com/repos/youhusky/youhusky.github.io/commits/30ccca9b2fc8c88b1d37c4bb595a8ec60414a4c8/comments",
        "author": null,
        "committer": null,
        "parents": [
            {
                "sha": "e94f67c91cd9363232920e3a02293fae71789147",
                "url": "https://api.github.com/repos/youhusky/youhusky.github.io/commits/e94f67c91cd9363232920e3a02293fae71789147",
                "html_url": "https://github.com/youhusky/youhusky.github.io/commit/e94f67c91cd9363232920e3a02293fae71789147"
            }
        ]
    },
    {
        "sha": "e94f67c91cd9363232920e3a02293fae71789147",
        "node_id": "MDY6Q29tbWl0Njk2MzMyODk6ZTk0ZjY3YzkxY2Q5MzYzMjMyOTIwZTNhMDIyOTNmYWU3MTc4OTE0Nw==",
        "commit": {
            "author": {
                "name": "Bozhao Li",
                "email": "youhusky@126.com",
                "date": "2016-11-30T02:03:48Z"
            },
            "committer": {
                "name": "Bozhao Li",
                "email": "youhusky@126.com",
                "date": "2016-11-30T02:03:48Z"
            },
            "message": "\u201c1129\u201d",
            "tree": {
                "sha": "5fce3898ef4daf1c278f1e7e39d33e3da94e7276",
                "url": "https://api.github.com/repos/youhusky/youhusky.github.io/git/trees/5fce3898ef4daf1c278f1e7e39d33e3da94e7276"
            },
            "url": "https://api.github.com/repos/youhusky/youhusky.github.io/git/commits/e94f67c91cd9363232920e3a02293fae71789147",
            "comment_count": 0,
            "verification": {
                "verified": false,
                "reason": "unsigned",
                "signature": null,
                "payload": null
            }
        },
        "url": "https://api.github.com/repos/youhusky/youhusky.github.io/commits/e94f67c91cd9363232920e3a02293fae71789147",
        "html_url": "https://github.com/youhusky/youhusky.github.io/commit/e94f67c91cd9363232920e3a02293fae71789147",
        "comments_url": "https://api.github.com/repos/youhusky/youhusky.github.io/commits/e94f67c91cd9363232920e3a02293fae71789147/comments",
        "author": null,
        "committer": null,
        "parents": [
            {
                "sha": "ba3feacaa0d4a45aba86f6b42f83ef81d7d1cabf",
                "url": "https://api.github.com/repos/youhusky/youhusky.github.io/commits/ba3feacaa0d4a45aba86f6b42f83ef81d7d1cabf",
                "html_url": "https://github.com/youhusky/youhusky.github.io/commit/ba3feacaa0d4a45aba86f6b42f83ef81d7d1cabf"
            }
        ]
    },
    {
        "sha": "ba3feacaa0d4a45aba86f6b42f83ef81d7d1cabf",
        "node_id": "MDY6Q29tbWl0Njk2MzMyODk6YmEzZmVhY2FhMGQ0YTQ1YWJhODZmNmI0MmY4M2VmODFkN2QxY2FiZg==",
        "commit": {
            "author": {
                "name": "Bozhao Li",
                "email": "youhusky@126.com",
                "date": "2016-11-28T19:35:06Z"
            },
            "committer": {
                "name": "Bozhao Li",
                "email": "youhusky@126.com",
                "date": "2016-11-28T19:35:06Z"
            },
            "message": "change",
            "tree": {
                "sha": "3e9e33523ba780ccf9f1228ea395375d5968943f",
                "url": "https://api.github.com/repos/youhusky/youhusky.github.io/git/trees/3e9e33523ba780ccf9f1228ea395375d5968943f"
            },
            "url": "https://api.github.com/repos/youhusky/youhusky.github.io/git/commits/ba3feacaa0d4a45aba86f6b42f83ef81d7d1cabf",
            "comment_count": 0,
            "verification": {
                "verified": false,
                "reason": "unsigned",
                "signature": null,
                "payload": null
            }
        },
        "url": "https://api.github.com/repos/youhusky/youhusky.github.io/commits/ba3feacaa0d4a45aba86f6b42f83ef81d7d1cabf",
        "html_url": "https://github.com/youhusky/youhusky.github.io/commit/ba3feacaa0d4a45aba86f6b42f83ef81d7d1cabf",
        "comments_url": "https://api.github.com/repos/youhusky/youhusky.github.io/commits/ba3feacaa0d4a45aba86f6b42f83ef81d7d1cabf/comments",
        "author": null,
        "committer": null,
        "parents": [
            {
                "sha": "4835d14cb5028440db71cc4ab6e25f650f45832a",
                "url": "https://api.github.com/repos/youhusky/youhusky.github.io/commits/4835d14cb5028440db71cc4ab6e25f650f45832a",
                "html_url": "https://github.com/youhusky/youhusky.github.io/commit/4835d14cb5028440db71cc4ab6e25f650f45832a"
            }
        ]
    },
    {
        "sha": "4835d14cb5028440db71cc4ab6e25f650f45832a",
        "node_id": "MDY6Q29tbWl0Njk2MzMyODk6NDgzNWQxNGNiNTAyODQ0MGRiNzFjYzRhYjZlMjVmNjUwZjQ1ODMyYQ==",
        "commit": {
            "author": {
                "name": "Bozhao Li",
                "email": "youhusky@126.com",
                "date": "2016-11-28T19:20:28Z"
            },
            "committer": {
                "name": "Bozhao Li",
                "email": "youhusky@126.com",
                "date": "2016-11-28T19:20:28Z"
            },
            "message": "3nd-joshua",
            "tree": {
                "sha": "e9d8625606b5834225a40d23820e0717816f9692",
                "url": "https://api.github.com/repos/youhusky/youhusky.github.io/git/trees/e9d8625606b5834225a40d23820e0717816f9692"
            },
            "url": "https://api.github.com/repos/youhusky/youhusky.github.io/git/commits/4835d14cb5028440db71cc4ab6e25f650f45832a",
            "comment_count": 0,
            "verification": {
                "verified": false,
                "reason": "unsigned",
                "signature": null,
                "payload": null
            }
        },
        "url": "https://api.github.com/repos/youhusky/youhusky.github.io/commits/4835d14cb5028440db71cc4ab6e25f650f45832a",
        "html_url": "https://github.com/youhusky/youhusky.github.io/commit/4835d14cb5028440db71cc4ab6e25f650f45832a",
        "comments_url": "https://api.github.com/repos/youhusky/youhusky.github.io/commits/4835d14cb5028440db71cc4ab6e25f650f45832a/comments",
        "author": null,
        "committer": null,
        "parents": [
            {
                "sha": "90547b308a62ce3c0cc35ddc67fa5ed6fd08f89f",
                "url": "https://api.github.com/repos/youhusky/youhusky.github.io/commits/90547b308a62ce3c0cc35ddc67fa5ed6fd08f89f",
                "html_url": "https://github.com/youhusky/youhusky.github.io/commit/90547b308a62ce3c0cc35ddc67fa5ed6fd08f89f"
            }
        ]
    },
    {
        "sha": "90547b308a62ce3c0cc35ddc67fa5ed6fd08f89f",
        "node_id": "MDY6Q29tbWl0Njk2MzMyODk6OTA1NDdiMzA4YTYyY2UzYzBjYzM1ZGRjNjdmYTVlZDZmZDA4Zjg5Zg==",
        "commit": {
            "author": {
                "name": "Bozhao Li",
                "email": "youhusky@126.com",
                "date": "2016-11-28T19:16:49Z"
            },
            "committer": {
                "name": "Bozhao Li",
                "email": "youhusky@126.com",
                "date": "2016-11-28T19:16:49Z"
            },
            "message": "project-2nd",
            "tree": {
                "sha": "0a86ca1a359f6aad5bc4757ef404f8cd9856aeb6",
                "url": "https://api.github.com/repos/youhusky/youhusky.github.io/git/trees/0a86ca1a359f6aad5bc4757ef404f8cd9856aeb6"
            },
            "url": "https://api.github.com/repos/youhusky/youhusky.github.io/git/commits/90547b308a62ce3c0cc35ddc67fa5ed6fd08f89f",
            "comment_count": 0,
            "verification": {
                "verified": false,
                "reason": "unsigned",
                "signature": null,
                "payload": null
            }
        },
        "url": "https://api.github.com/repos/youhusky/youhusky.github.io/commits/90547b308a62ce3c0cc35ddc67fa5ed6fd08f89f",
        "html_url": "https://github.com/youhusky/youhusky.github.io/commit/90547b308a62ce3c0cc35ddc67fa5ed6fd08f89f",
        "comments_url": "https://api.github.com/repos/youhusky/youhusky.github.io/commits/90547b308a62ce3c0cc35ddc67fa5ed6fd08f89f/comments",
        "author": null,
        "committer": null,
        "parents": [
            {
                "sha": "72cf2357e85ee9be65180ea119919e9d7500b941",
                "url": "https://api.github.com/repos/youhusky/youhusky.github.io/commits/72cf2357e85ee9be65180ea119919e9d7500b941",
                "html_url": "https://github.com/youhusky/youhusky.github.io/commit/72cf2357e85ee9be65180ea119919e9d7500b941"
            }
        ]
    },
    {
        "sha": "72cf2357e85ee9be65180ea119919e9d7500b941",
        "node_id": "MDY6Q29tbWl0Njk2MzMyODk6NzJjZjIzNTdlODVlZTliZTY1MTgwZWExMTk5MTllOWQ3NTAwYjk0MQ==",
        "commit": {
            "author": {
                "name": "Bozhao Li",
                "email": "youhusky@126.com",
                "date": "2016-11-28T19:06:41Z"
            },
            "committer": {
                "name": "Bozhao Li",
                "email": "youhusky@126.com",
                "date": "2016-11-28T19:07:24Z"
            },
            "message": "project",
            "tree": {
                "sha": "91d08adb12eff87d86b2ac60d3a6b5ff8e6e4393",
                "url": "https://api.github.com/repos/youhusky/youhusky.github.io/git/trees/91d08adb12eff87d86b2ac60d3a6b5ff8e6e4393"
            },
            "url": "https://api.github.com/repos/youhusky/youhusky.github.io/git/commits/72cf2357e85ee9be65180ea119919e9d7500b941",
            "comment_count": 0,
            "verification": {
                "verified": false,
                "reason": "unsigned",
                "signature": null,
                "payload": null
            }
        },
        "url": "https://api.github.com/repos/youhusky/youhusky.github.io/commits/72cf2357e85ee9be65180ea119919e9d7500b941",
        "html_url": "https://github.com/youhusky/youhusky.github.io/commit/72cf2357e85ee9be65180ea119919e9d7500b941",
        "comments_url": "https://api.github.com/repos/youhusky/youhusky.github.io/commits/72cf2357e85ee9be65180ea119919e9d7500b941/comments",
        "author": null,
        "committer": null,
        "parents": [
            {
                "sha": "1e3741f6c097c8790caa7c573f681cc99e267de6",
                "url": "https://api.github.com/repos/youhusky/youhusky.github.io/commits/1e3741f6c097c8790caa7c573f681cc99e267de6",
                "html_url": "https://github.com/youhusky/youhusky.github.io/commit/1e3741f6c097c8790caa7c573f681cc99e267de6"
            }
        ]
    },
    {
        "sha": "1e3741f6c097c8790caa7c573f681cc99e267de6",
        "node_id": "MDY6Q29tbWl0Njk2MzMyODk6MWUzNzQxZjZjMDk3Yzg3OTBjYWE3YzU3M2Y2ODFjYzk5ZTI2N2RlNg==",
        "commit": {
            "author": {
                "name": "Bozhao(Joshua) Li",
                "email": "bozhaoli@usc.edu",
                "date": "2016-10-03T19:55:07Z"
            },
            "committer": {
                "name": "GitHub",
                "email": "noreply@github.com",
                "date": "2016-10-03T19:55:07Z"
            },
            "message": "Create LICENSE",
            "tree": {
                "sha": "7fcda64795553d59848596e2d1e29080164c5994",
                "url": "https://api.github.com/repos/youhusky/youhusky.github.io/git/trees/7fcda64795553d59848596e2d1e29080164c5994"
            },
            "url": "https://api.github.com/repos/youhusky/youhusky.github.io/git/commits/1e3741f6c097c8790caa7c573f681cc99e267de6",
            "comment_count": 0,
            "verification": {
                "verified": false,
                "reason": "unsigned",
                "signature": null,
                "payload": null
            }
        },
        "url": "https://api.github.com/repos/youhusky/youhusky.github.io/commits/1e3741f6c097c8790caa7c573f681cc99e267de6",
        "html_url": "https://github.com/youhusky/youhusky.github.io/commit/1e3741f6c097c8790caa7c573f681cc99e267de6",
        "comments_url": "https://api.github.com/repos/youhusky/youhusky.github.io/commits/1e3741f6c097c8790caa7c573f681cc99e267de6/comments",
        "author": {
            "login": "youhusky",
            "id": 10191895,
            "node_id": "MDQ6VXNlcjEwMTkxODk1",
            "avatar_url": "https://avatars3.githubusercontent.com/u/10191895?v=4",
            "gravatar_id": "",
            "url": "https://api.github.com/users/youhusky",
            "html_url": "https://github.com/youhusky",
            "followers_url": "https://api.github.com/users/youhusky/followers",
            "following_url": "https://api.github.com/users/youhusky/following{/other_user}",
            "gists_url": "https://api.github.com/users/youhusky/gists{/gist_id}",
            "starred_url": "https://api.github.com/users/youhusky/starred{/owner}{/repo}",
            "subscriptions_url": "https://api.github.com/users/youhusky/subscriptions",
            "organizations_url": "https://api.github.com/users/youhusky/orgs",
            "repos_url": "https://api.github.com/users/youhusky/repos",
            "events_url": "https://api.github.com/users/youhusky/events{/privacy}",
            "received_events_url": "https://api.github.com/users/youhusky/received_events",
            "type": "User",
            "site_admin": false
        },
        "committer": {
            "login": "web-flow",
            "id": 19864447,
            "node_id": "MDQ6VXNlcjE5ODY0NDQ3",
            "avatar_url": "https://avatars3.githubusercontent.com/u/19864447?v=4",
            "gravatar_id": "",
            "url": "https://api.github.com/users/web-flow",
            "html_url": "https://github.com/web-flow",
            "followers_url": "https://api.github.com/users/web-flow/followers",
            "following_url": "https://api.github.com/users/web-flow/following{/other_user}",
            "gists_url": "https://api.github.com/users/web-flow/gists{/gist_id}",
            "starred_url": "https://api.github.com/users/web-flow/starred{/owner}{/repo}",
            "subscriptions_url": "https://api.github.com/users/web-flow/subscriptions",
            "organizations_url": "https://api.github.com/users/web-flow/orgs",
            "repos_url": "https://api.github.com/users/web-flow/repos",
            "events_url": "https://api.github.com/users/web-flow/events{/privacy}",
            "received_events_url": "https://api.github.com/users/web-flow/received_events",
            "type": "User",
            "site_admin": false
        },
        "parents": [
            {
                "sha": "8221f92c06af691983f72e8356179b93643acd1f",
                "url": "https://api.github.com/repos/youhusky/youhusky.github.io/commits/8221f92c06af691983f72e8356179b93643acd1f",
                "html_url": "https://github.com/youhusky/youhusky.github.io/commit/8221f92c06af691983f72e8356179b93643acd1f"
            }
        ]
    },
    {
        "sha": "8221f92c06af691983f72e8356179b93643acd1f",
        "node_id": "MDY6Q29tbWl0Njk2MzMyODk6ODIyMWY5MmMwNmFmNjkxOTgzZjcyZTgzNTYxNzliOTM2NDNhY2QxZg==",
        "commit": {
            "author": {
                "name": "Bozhao Li",
                "email": "youhusky@126.com",
                "date": "2016-10-02T00:03:29Z"
            },
            "committer": {
                "name": "Bozhao Li",
                "email": "youhusky@126.com",
                "date": "2016-10-02T00:03:29Z"
            },
            "message": "test",
            "tree": {
                "sha": "4b7298f15d88c919d5593704cb36f42ac9c9fdc0",
                "url": "https://api.github.com/repos/youhusky/youhusky.github.io/git/trees/4b7298f15d88c919d5593704cb36f42ac9c9fdc0"
            },
            "url": "https://api.github.com/repos/youhusky/youhusky.github.io/git/commits/8221f92c06af691983f72e8356179b93643acd1f",
            "comment_count": 0,
            "verification": {
                "verified": false,
                "reason": "unsigned",
                "signature": null,
                "payload": null
            }
        },
        "url": "https://api.github.com/repos/youhusky/youhusky.github.io/commits/8221f92c06af691983f72e8356179b93643acd1f",
        "html_url": "https://github.com/youhusky/youhusky.github.io/commit/8221f92c06af691983f72e8356179b93643acd1f",
        "comments_url": "https://api.github.com/repos/youhusky/youhusky.github.io/commits/8221f92c06af691983f72e8356179b93643acd1f/comments",
        "author": null,
        "committer": null,
        "parents": [
            {
                "sha": "546402cb94d88278164841bdede680612bdc4100",
                "url": "https://api.github.com/repos/youhusky/youhusky.github.io/commits/546402cb94d88278164841bdede680612bdc4100",
                "html_url": "https://github.com/youhusky/youhusky.github.io/commit/546402cb94d88278164841bdede680612bdc4100"
            }
        ]
    },
    {
        "sha": "546402cb94d88278164841bdede680612bdc4100",
        "node_id": "MDY6Q29tbWl0Njk2MzMyODk6NTQ2NDAyY2I5NGQ4ODI3ODE2NDg0MWJkZWRlNjgwNjEyYmRjNDEwMA==",
        "commit": {
            "author": {
                "name": "Bozhao Li",
                "email": "youhusky@126.com",
                "date": "2016-10-02T00:01:44Z"
            },
            "committer": {
                "name": "Bozhao Li",
                "email": "youhusky@126.com",
                "date": "2016-10-02T00:01:44Z"
            },
            "message": "test",
            "tree": {
                "sha": "1134bd752d938b8835821c4816e49de793a47d1c",
                "url": "https://api.github.com/repos/youhusky/youhusky.github.io/git/trees/1134bd752d938b8835821c4816e49de793a47d1c"
            },
            "url": "https://api.github.com/repos/youhusky/youhusky.github.io/git/commits/546402cb94d88278164841bdede680612bdc4100",
            "comment_count": 0,
            "verification": {
                "verified": false,
                "reason": "unsigned",
                "signature": null,
                "payload": null
            }
        },
        "url": "https://api.github.com/repos/youhusky/youhusky.github.io/commits/546402cb94d88278164841bdede680612bdc4100",
        "html_url": "https://github.com/youhusky/youhusky.github.io/commit/546402cb94d88278164841bdede680612bdc4100",
        "comments_url": "https://api.github.com/repos/youhusky/youhusky.github.io/commits/546402cb94d88278164841bdede680612bdc4100/comments",
        "author": null,
        "committer": null,
        "parents": [
            {
                "sha": "62380b3a0070344994bf6fc50b933ea847a66974",
                "url": "https://api.github.com/repos/youhusky/youhusky.github.io/commits/62380b3a0070344994bf6fc50b933ea847a66974",
                "html_url": "https://github.com/youhusky/youhusky.github.io/commit/62380b3a0070344994bf6fc50b933ea847a66974"
            }
        ]
    },
    {
        "sha": "62380b3a0070344994bf6fc50b933ea847a66974",
        "node_id": "MDY6Q29tbWl0Njk2MzMyODk6NjIzODBiM2EwMDcwMzQ0OTk0YmY2ZmM1MGI5MzNlYTg0N2E2Njk3NA==",
        "commit": {
            "author": {
                "name": "Bozhao Li",
                "email": "youhusky@126.com",
                "date": "2016-10-02T00:00:56Z"
            },
            "committer": {
                "name": "Bozhao Li",
                "email": "youhusky@126.com",
                "date": "2016-10-02T00:00:56Z"
            },
            "message": "test",
            "tree": {
                "sha": "485187a089b43ed2ae24c475900198644424db72",
                "url": "https://api.github.com/repos/youhusky/youhusky.github.io/git/trees/485187a089b43ed2ae24c475900198644424db72"
            },
            "url": "https://api.github.com/repos/youhusky/youhusky.github.io/git/commits/62380b3a0070344994bf6fc50b933ea847a66974",
            "comment_count": 0,
            "verification": {
                "verified": false,
                "reason": "unsigned",
                "signature": null,
                "payload": null
            }
        },
        "url": "https://api.github.com/repos/youhusky/youhusky.github.io/commits/62380b3a0070344994bf6fc50b933ea847a66974",
        "html_url": "https://github.com/youhusky/youhusky.github.io/commit/62380b3a0070344994bf6fc50b933ea847a66974",
        "comments_url": "https://api.github.com/repos/youhusky/youhusky.github.io/commits/62380b3a0070344994bf6fc50b933ea847a66974/comments",
        "author": null,
        "committer": null,
        "parents": [
            {
                "sha": "4ad7f7604080be501586b94c8af02e7b15ce47e0",
                "url": "https://api.github.com/repos/youhusky/youhusky.github.io/commits/4ad7f7604080be501586b94c8af02e7b15ce47e0",
                "html_url": "https://github.com/youhusky/youhusky.github.io/commit/4ad7f7604080be501586b94c8af02e7b15ce47e0"
            }
        ]
    },
    {
        "sha": "4ad7f7604080be501586b94c8af02e7b15ce47e0",
        "node_id": "MDY6Q29tbWl0Njk2MzMyODk6NGFkN2Y3NjA0MDgwYmU1MDE1ODZiOTRjOGFmMDJlN2IxNWNlNDdlMA==",
        "commit": {
            "author": {
                "name": "Bozhao Li",
                "email": "youhusky@126.com",
                "date": "2016-09-30T05:59:18Z"
            },
            "committer": {
                "name": "Bozhao Li",
                "email": "youhusky@126.com",
                "date": "2016-09-30T05:59:18Z"
            },
            "message": "edit",
            "tree": {
                "sha": "e5bb10d0295bba9853b0f60907e8dfec9b549c77",
                "url": "https://api.github.com/repos/youhusky/youhusky.github.io/git/trees/e5bb10d0295bba9853b0f60907e8dfec9b549c77"
            },
            "url": "https://api.github.com/repos/youhusky/youhusky.github.io/git/commits/4ad7f7604080be501586b94c8af02e7b15ce47e0",
            "comment_count": 0,
            "verification": {
                "verified": false,
                "reason": "unsigned",
                "signature": null,
                "payload": null
            }
        },
        "url": "https://api.github.com/repos/youhusky/youhusky.github.io/commits/4ad7f7604080be501586b94c8af02e7b15ce47e0",
        "html_url": "https://github.com/youhusky/youhusky.github.io/commit/4ad7f7604080be501586b94c8af02e7b15ce47e0",
        "comments_url": "https://api.github.com/repos/youhusky/youhusky.github.io/commits/4ad7f7604080be501586b94c8af02e7b15ce47e0/comments",
        "author": null,
        "committer": null,
        "parents": [
            {
                "sha": "bde9cbd07c6309fbdc20c21ad5ace65513e51028",
                "url": "https://api.github.com/repos/youhusky/youhusky.github.io/commits/bde9cbd07c6309fbdc20c21ad5ace65513e51028",
                "html_url": "https://github.com/youhusky/youhusky.github.io/commit/bde9cbd07c6309fbdc20c21ad5ace65513e51028"
            }
        ]
    },
    {
        "sha": "bde9cbd07c6309fbdc20c21ad5ace65513e51028",
        "node_id": "MDY6Q29tbWl0Njk2MzMyODk6YmRlOWNiZDA3YzYzMDlmYmRjMjBjMjFhZDVhY2U2NTUxM2U1MTAyOA==",
        "commit": {
            "author": {
                "name": "Bozhao Li",
                "email": "youhusky@126.com",
                "date": "2016-09-30T05:54:34Z"
            },
            "committer": {
                "name": "Bozhao Li",
                "email": "youhusky@126.com",
                "date": "2016-09-30T05:54:34Z"
            },
            "message": "edit",
            "tree": {
                "sha": "5828540b70755e439909149bf75353e4a90bd036",
                "url": "https://api.github.com/repos/youhusky/youhusky.github.io/git/trees/5828540b70755e439909149bf75353e4a90bd036"
            },
            "url": "https://api.github.com/repos/youhusky/youhusky.github.io/git/commits/bde9cbd07c6309fbdc20c21ad5ace65513e51028",
            "comment_count": 0,
            "verification": {
                "verified": false,
                "reason": "unsigned",
                "signature": null,
                "payload": null
            }
        },
        "url": "https://api.github.com/repos/youhusky/youhusky.github.io/commits/bde9cbd07c6309fbdc20c21ad5ace65513e51028",
        "html_url": "https://github.com/youhusky/youhusky.github.io/commit/bde9cbd07c6309fbdc20c21ad5ace65513e51028",
        "comments_url": "https://api.github.com/repos/youhusky/youhusky.github.io/commits/bde9cbd07c6309fbdc20c21ad5ace65513e51028/comments",
        "author": null,
        "committer": null,
        "parents": [
            {
                "sha": "649a74656a107585d2d4d2fc39b270df74f322cc",
                "url": "https://api.github.com/repos/youhusky/youhusky.github.io/commits/649a74656a107585d2d4d2fc39b270df74f322cc",
                "html_url": "https://github.com/youhusky/youhusky.github.io/commit/649a74656a107585d2d4d2fc39b270df74f322cc"
            }
        ]
    },
    {
        "sha": "649a74656a107585d2d4d2fc39b270df74f322cc",
        "node_id": "MDY6Q29tbWl0Njk2MzMyODk6NjQ5YTc0NjU2YTEwNzU4NWQyZDRkMmZjMzliMjcwZGY3NGYzMjJjYw==",
        "commit": {
            "author": {
                "name": "Bozhao(Joshua) Li",
                "email": "bozhaoli@usc.edu",
                "date": "2016-09-30T04:21:01Z"
            },
            "committer": {
                "name": "Bozhao(Joshua) Li",
                "email": "bozhaoli@usc.edu",
                "date": "2016-09-30T04:21:01Z"
            },
            "message": "Create CNAME",
            "tree": {
                "sha": "5e1a11e91a4bba6e711df0e877129516acefc919",
                "url": "https://api.github.com/repos/youhusky/youhusky.github.io/git/trees/5e1a11e91a4bba6e711df0e877129516acefc919"
            },
            "url": "https://api.github.com/repos/youhusky/youhusky.github.io/git/commits/649a74656a107585d2d4d2fc39b270df74f322cc",
            "comment_count": 0,
            "verification": {
                "verified": false,
                "reason": "unsigned",
                "signature": null,
                "payload": null
            }
        },
        "url": "https://api.github.com/repos/youhusky/youhusky.github.io/commits/649a74656a107585d2d4d2fc39b270df74f322cc",
        "html_url": "https://github.com/youhusky/youhusky.github.io/commit/649a74656a107585d2d4d2fc39b270df74f322cc",
        "comments_url": "https://api.github.com/repos/youhusky/youhusky.github.io/commits/649a74656a107585d2d4d2fc39b270df74f322cc/comments",
        "author": {
            "login": "youhusky",
            "id": 10191895,
            "node_id": "MDQ6VXNlcjEwMTkxODk1",
            "avatar_url": "https://avatars3.githubusercontent.com/u/10191895?v=4",
            "gravatar_id": "",
            "url": "https://api.github.com/users/youhusky",
            "html_url": "https://github.com/youhusky",
            "followers_url": "https://api.github.com/users/youhusky/followers",
            "following_url": "https://api.github.com/users/youhusky/following{/other_user}",
            "gists_url": "https://api.github.com/users/youhusky/gists{/gist_id}",
            "starred_url": "https://api.github.com/users/youhusky/starred{/owner}{/repo}",
            "subscriptions_url": "https://api.github.com/users/youhusky/subscriptions",
            "organizations_url": "https://api.github.com/users/youhusky/orgs",
            "repos_url": "https://api.github.com/users/youhusky/repos",
            "events_url": "https://api.github.com/users/youhusky/events{/privacy}",
            "received_events_url": "https://api.github.com/users/youhusky/received_events",
            "type": "User",
            "site_admin": false
        },
        "committer": {
            "login": "youhusky",
            "id": 10191895,
            "node_id": "MDQ6VXNlcjEwMTkxODk1",
            "avatar_url": "https://avatars3.githubusercontent.com/u/10191895?v=4",
            "gravatar_id": "",
            "url": "https://api.github.com/users/youhusky",
            "html_url": "https://github.com/youhusky",
            "followers_url": "https://api.github.com/users/youhusky/followers",
            "following_url": "https://api.github.com/users/youhusky/following{/other_user}",
            "gists_url": "https://api.github.com/users/youhusky/gists{/gist_id}",
            "starred_url": "https://api.github.com/users/youhusky/starred{/owner}{/repo}",
            "subscriptions_url": "https://api.github.com/users/youhusky/subscriptions",
            "organizations_url": "https://api.github.com/users/youhusky/orgs",
            "repos_url": "https://api.github.com/users/youhusky/repos",
            "events_url": "https://api.github.com/users/youhusky/events{/privacy}",
            "received_events_url": "https://api.github.com/users/youhusky/received_events",
            "type": "User",
            "site_admin": false
        },
        "parents": [
            {
                "sha": "7a76c9802a36e2703a56a7cf7aa7e070f1b71c9a",
                "url": "https://api.github.com/repos/youhusky/youhusky.github.io/commits/7a76c9802a36e2703a56a7cf7aa7e070f1b71c9a",
                "html_url": "https://github.com/youhusky/youhusky.github.io/commit/7a76c9802a36e2703a56a7cf7aa7e070f1b71c9a"
            }
        ]
    },
    {
        "sha": "7a76c9802a36e2703a56a7cf7aa7e070f1b71c9a",
        "node_id": "MDY6Q29tbWl0Njk2MzMyODk6N2E3NmM5ODAyYTM2ZTI3MDNhNTZhN2NmN2FhN2UwNzBmMWI3MWM5YQ==",
        "commit": {
            "author": {
                "name": "Bozhao(Joshua) Li",
                "email": "bozhaoli@usc.edu",
                "date": "2016-09-30T04:20:43Z"
            },
            "committer": {
                "name": "Bozhao(Joshua) Li",
                "email": "bozhaoli@usc.edu",
                "date": "2016-09-30T04:20:43Z"
            },
            "message": "Initial commit",
            "tree": {
                "sha": "981e8af444e71d738a28d4933004adfa9eb43ee3",
                "url": "https://api.github.com/repos/youhusky/youhusky.github.io/git/trees/981e8af444e71d738a28d4933004adfa9eb43ee3"
            },
            "url": "https://api.github.com/repos/youhusky/youhusky.github.io/git/commits/7a76c9802a36e2703a56a7cf7aa7e070f1b71c9a",
            "comment_count": 0,
            "verification": {
                "verified": false,
                "reason": "unsigned",
                "signature": null,
                "payload": null
            }
        },
        "url": "https://api.github.com/repos/youhusky/youhusky.github.io/commits/7a76c9802a36e2703a56a7cf7aa7e070f1b71c9a",
        "html_url": "https://github.com/youhusky/youhusky.github.io/commit/7a76c9802a36e2703a56a7cf7aa7e070f1b71c9a",
        "comments_url": "https://api.github.com/repos/youhusky/youhusky.github.io/commits/7a76c9802a36e2703a56a7cf7aa7e070f1b71c9a/comments",
        "author": {
            "login": "youhusky",
            "id": 10191895,
            "node_id": "MDQ6VXNlcjEwMTkxODk1",
            "avatar_url": "https://avatars3.githubusercontent.com/u/10191895?v=4",
            "gravatar_id": "",
            "url": "https://api.github.com/users/youhusky",
            "html_url": "https://github.com/youhusky",
            "followers_url": "https://api.github.com/users/youhusky/followers",
            "following_url": "https://api.github.com/users/youhusky/following{/other_user}",
            "gists_url": "https://api.github.com/users/youhusky/gists{/gist_id}",
            "starred_url": "https://api.github.com/users/youhusky/starred{/owner}{/repo}",
            "subscriptions_url": "https://api.github.com/users/youhusky/subscriptions",
            "organizations_url": "https://api.github.com/users/youhusky/orgs",
            "repos_url": "https://api.github.com/users/youhusky/repos",
            "events_url": "https://api.github.com/users/youhusky/events{/privacy}",
            "received_events_url": "https://api.github.com/users/youhusky/received_events",
            "type": "User",
            "site_admin": false
        },
        "committer": {
            "login": "youhusky",
            "id": 10191895,
            "node_id": "MDQ6VXNlcjEwMTkxODk1",
            "avatar_url": "https://avatars3.githubusercontent.com/u/10191895?v=4",
            "gravatar_id": "",
            "url": "https://api.github.com/users/youhusky",
            "html_url": "https://github.com/youhusky",
            "followers_url": "https://api.github.com/users/youhusky/followers",
            "following_url": "https://api.github.com/users/youhusky/following{/other_user}",
            "gists_url": "https://api.github.com/users/youhusky/gists{/gist_id}",
            "starred_url": "https://api.github.com/users/youhusky/starred{/owner}{/repo}",
            "subscriptions_url": "https://api.github.com/users/youhusky/subscriptions",
            "organizations_url": "https://api.github.com/users/youhusky/orgs",
            "repos_url": "https://api.github.com/users/youhusky/repos",
            "events_url": "https://api.github.com/users/youhusky/events{/privacy}",
            "received_events_url": "https://api.github.com/users/youhusky/received_events",
            "type": "User",
            "site_admin": false
        },
        "parents": []
    }
]