[
    {
        "login": "jjlee050",
        "id": 5901764,
        "node_id": "MDQ6VXNlcjU5MDE3NjQ=",
        "avatar_url": "https://avatars2.githubusercontent.com/u/5901764?v=4",
        "gravatar_id": "",
        "url": "https://api.github.com/users/jjlee050",
        "html_url": "https://github.com/jjlee050",
        "followers_url": "https://api.github.com/users/jjlee050/followers",
        "following_url": "https://api.github.com/users/jjlee050/following{/other_user}",
        "gists_url": "https://api.github.com/users/jjlee050/gists{/gist_id}",
        "starred_url": "https://api.github.com/users/jjlee050/starred{/owner}{/repo}",
        "subscriptions_url": "https://api.github.com/users/jjlee050/subscriptions",
        "organizations_url": "https://api.github.com/users/jjlee050/orgs",
        "repos_url": "https://api.github.com/users/jjlee050/repos",
        "events_url": "https://api.github.com/users/jjlee050/events{/privacy}",
        "received_events_url": "https://api.github.com/users/jjlee050/received_events",
        "type": "User",
        "site_admin": false,
        "contributions": 32
    },
    {
        "login": "Sheikh-Umar",
        "id": 35603008,
        "node_id": "MDQ6VXNlcjM1NjAzMDA4",
        "avatar_url": "https://avatars3.githubusercontent.com/u/35603008?v=4",
        "gravatar_id": "",
        "url": "https://api.github.com/users/Sheikh-Umar",
        "html_url": "https://github.com/Sheikh-Umar",
        "followers_url": "https://api.github.com/users/Sheikh-Umar/followers",
        "following_url": "https://api.github.com/users/Sheikh-Umar/following{/other_user}",
        "gists_url": "https://api.github.com/users/Sheikh-Umar/gists{/gist_id}",
        "starred_url": "https://api.github.com/users/Sheikh-Umar/starred{/owner}{/repo}",
        "subscriptions_url": "https://api.github.com/users/Sheikh-Umar/subscriptions",
        "organizations_url": "https://api.github.com/users/Sheikh-Umar/orgs",
        "repos_url": "https://api.github.com/users/Sheikh-Umar/repos",
        "events_url": "https://api.github.com/users/Sheikh-Umar/events{/privacy}",
        "received_events_url": "https://api.github.com/users/Sheikh-Umar/received_events",
        "type": "User",
        "site_admin": false,
        "contributions": 9
    },
    {
        "login": "shahidee44",
        "id": 36878360,
        "node_id": "MDQ6VXNlcjM2ODc4MzYw",
        "avatar_url": "https://avatars3.githubusercontent.com/u/36878360?v=4",
        "gravatar_id": "",
        "url": "https://api.github.com/users/shahidee44",
        "html_url": "https://github.com/shahidee44",
        "followers_url": "https://api.github.com/users/shahidee44/followers",
        "following_url": "https://api.github.com/users/shahidee44/following{/other_user}",
        "gists_url": "https://api.github.com/users/shahidee44/gists{/gist_id}",
        "starred_url": "https://api.github.com/users/shahidee44/starred{/owner}{/repo}",
        "subscriptions_url": "https://api.github.com/users/shahidee44/subscriptions",
        "organizations_url": "https://api.github.com/users/shahidee44/orgs",
        "repos_url": "https://api.github.com/users/shahidee44/repos",
        "events_url": "https://api.github.com/users/shahidee44/events{/privacy}",
        "received_events_url": "https://api.github.com/users/shahidee44/received_events",
        "type": "User",
        "site_admin": false,
        "contributions": 6
    },
    {
        "login": "JohnWnx",
        "id": 40804580,
        "node_id": "MDQ6VXNlcjQwODA0NTgw",
        "avatar_url": "https://avatars3.githubusercontent.com/u/40804580?v=4",
        "gravatar_id": "",
        "url": "https://api.github.com/users/JohnWnx",
        "html_url": "https://github.com/JohnWnx",
        "followers_url": "https://api.github.com/users/JohnWnx/followers",
        "following_url": "https://api.github.com/users/JohnWnx/following{/other_user}",
        "gists_url": "https://api.github.com/users/JohnWnx/gists{/gist_id}",
        "starred_url": "https://api.github.com/users/JohnWnx/starred{/owner}{/repo}",
        "subscriptions_url": "https://api.github.com/users/JohnWnx/subscriptions",
        "organizations_url": "https://api.github.com/users/JohnWnx/orgs",
        "repos_url": "https://api.github.com/users/JohnWnx/repos",
        "events_url": "https://api.github.com/users/JohnWnx/events{/privacy}",
        "received_events_url": "https://api.github.com/users/JohnWnx/received_events",
        "type": "User",
        "site_admin": false,
        "contributions": 3
    }
]